Metadata-Version: 2.1
Name: invx
Version: 0.0.1
Summary: Securetia Investigation Tools (invx)
Home-page: https://www.securetia.com
Author: Fabian Martinez Portantier
Author-email: fabian@portantier.com
License: BSD 3-clause
Keywords: security
Platform: UNKNOWN
Classifier: Environment :: Console
Classifier: Intended Audience :: Developers
Classifier: Intended Audience :: Information Technology
Classifier: Intended Audience :: System Administrators
Classifier: License :: OSI Approved :: BSD License
Classifier: Topic :: Security
Classifier: Topic :: System :: Networking
Classifier: Programming Language :: Python :: 3.0
Classifier: Programming Language :: Python :: 3.7
